{
  "slug": "cheap-acura-uk",
  "title": "Buy a Cheap Acura in the UK | Reliability, Issues & Tips | BuyAndScrap",
  "metaDescription": "Dreaming of a cheap Acura in the UK? Discover the pros, cons, reliability, and essential buying tips for these unique Honda-built cars. Find your next Acura at BuyAndScrap!",
  "targetKeyword": "cheap acura UK",
  "intent": "commercial",
  "pillar": "makes",
  "internalLinks": [
    "sell-my-car",
    "honda-reliability-guide"
  ],
  "content": "# Buy a Cheap Acura in the UK: Your Guide to Reliability, Issues & Tips\n\nEver spotted an intriguing car on UK roads that looks a bit like a Honda, but not quite? Chances are, it might have been an Acura! While not officially sold in the UK, these premium vehicles – Honda's luxury arm – have found their way over as imports, offering a unique blend of Honda reliability with distinctive American styling.\n\nIf you're looking for something a bit different, perhaps a car that offers fantastic value for money and stands out from the usual German marques, then hunting for a **cheap Acura UK** might be just the adventure for you. But what exactly are you getting into? Let's dive in.\n\n## What Exactly is an Acura and Why Buy One in the UK?\n\nAcura is the luxury vehicle division of Japanese automaker Honda. Primarily aimed at the North American market, Acura models often share platforms and engines with their Honda counterparts, but feature more upscale interiors, advanced technology, and distinct styling. Think of it as Lexus to Toyota, or Infiniti to Nissan.\n\nIn the UK, finding an Acura means buying an import. This can be a brilliant way to get a well-built, reliable car with a bit of rarity factor, often for less than an equivalent premium European model. If you're after a **cheap Acura UK**, you're likely looking at models like the RSX (effectively an Integra Type-S), TSX (a sportier Honda Accord), TL, or the MDX SUV.\n\n## The Allure of a Cheap Acura: Pros & Cons\n\nBefore you jump into searching for a **cheap Acura UK**, it's wise to weigh up the good bits and the potential headaches.\n\n### The Pros of Owning an Acura\n\n*   **Honda Reliability:** This is perhaps the biggest draw. Acuras inherit Honda's legendary build quality and engineering, meaning they are generally very dependable, with engines and transmissions designed to go the distance.\n*   **Value for Money:** Because they're imports and not a mainstream brand here, Acuras often offer excellent value, allowing you to get a lot of car for your budget compared to a similar age/spec BMW, Audi, or Mercedes.\n*   **Uniqueness:** You won't see one on every street corner! Owning an Acura guarantees a degree of exclusivity and makes for an interesting conversation starter.\n*   **Performance:** Many Acura models, especially the RSX and TSX, offer engaging driving dynamics and lively Honda engines.\n\n### The Cons & Challenges to Consider\n\n*   **Parts Availability:** This is the main hurdle. While many mechanical parts are shared with Hondas, specific body panels, interior trim, or unique electrical components might need to be imported from the US, which can be costly and time-consuming.\n*   **Specialist Mechanics:** Not every local garage will be familiar with Acura-specific diagnostics or repairs. Finding a Honda specialist or a mechanic experienced with imports is crucial.\n*   **Insurance:** Due to their import status and relative rarity, insuring an Acura might be slightly more expensive than a domestic equivalent. Always get quotes before buying.\n*   **Resale Value:** While you might buy one cheaply, selling it on can be a niche market, potentially limiting your pool of buyers.\n*   **Left-Hand Drive:** Many imports will be left-hand drive, which takes some getting used to on UK roads.\n\n## Key Acura Models You Might Find in the UK\n\nHere are a few models that pop up on the UK used market, offering different experiences for someone looking for a cheap Acura:\n\n### Acura RSX (2001-2006)\n\nThe RSX is essentially the third-generation Honda Integra, known for its sporty coupe styling and fantastic VTEC engines. The Type-S variant is particularly sought after for its performance. Rust, particularly on the rear arches, can be an issue, as can worn suspension components.\n\n### Acura TSX (2003-2014)\n\nThis is the North American version of the European Honda Accord, but often with a sportier tune and more premium features. It's a fantastic, reliable saloon. Look out for potential automatic gearbox issues on higher mileage models, and ensure regular oil changes have been performed.\n\n### Acura TL (1995-2014)\n\nThe TL is a larger, more luxurious saloon. Earlier models are less common, but the third and fourth generations offer a lot of car for the money. Again, check automatic transmissions thoroughly, and ensure all electronics (which can be plentiful) are working correctly.\n\n### Acura MDX (2000-Present)\n\nFor those needing an SUV, the MDX is a sturdy, often seven-seater option. They share components with the Honda Pilot/CR-V. As with any SUV, check for signs of neglect, especially suspension and brake wear, and ensure the 4WD system (if applicable) is functioning.\n\n## Tips for Buying Your Cheap Acura in the UK\n\n1.  **Do Your Homework:** Research the specific model you're interested in. Join online forums (often US-based) to understand common issues and maintenance schedules.\n2.  **Inspect Thoroughly:** A full pre-purchase inspection by a reputable mechanic (preferably a Honda specialist) is non-negotiable. Pay close attention to rust, especially if the car spent time in harsh climates before import.\n3.  **Verify Service History:** Ensure the car has a comprehensive service record, ideally with evidence of regular maintenance. This is even more vital for imports.\n4.  **Factor in Costs:** Don't just look at the purchase price. Get insurance quotes, research parts prices, and consider the potential cost of specialist labour.\n5.  **Check Registration & MOT:** Ensure the car is fully UK registered, has a valid MOT, and that any necessary modifications for UK roads (like headlamps) have been properly done.\n\n## Final Thoughts on Finding Your Acura Bargain\n\nBuying a **cheap Acura UK** isn't for everyone, but for the enthusiast or the savvy buyer looking for something a bit out of the ordinary, it can be a really rewarding experience. You'll get Honda reliability wrapped in a unique, often luxurious package, all for a price that won't break the bank.\n\nJust be prepared for the minor challenges of parts and specialist knowledge, and you could be enjoying a fantastic, distinctive car that turns heads for all the right reasons.\n\nReady to find your next unique ride?\n\n",
  "wordCount": 776,
  "cta": "Browse Cheap Acura Cars",
  "ctaLink": "/cars"
}