{
  "slug": "how-to-make-your-budget-car-last-2-years",
  "title": "How to Make Your Budget Car Last 2 Years",
  "metaDescription": "Want to know how to make your budget car last 2 years? Our expert tips cover maintenance, driving habits, and clever tricks to extend your car's life. Get started now!",
  "targetKeyword": "how to make your budget car last 2 years",
  "intent": "commercial",
  "pillar": "budget",
  "internalLinks": [
    "what-to-look-for-when-buying-a-budget-car",
    "top-5-common-car-problems-and-fixes"
  ],
  "content": "# How to Make Your Budget Car Last 2 Years\n\nLet's be honest, buying a budget car often means you're looking for a reliable set of wheels without breaking the bank. The dream isn't a showroom model; it's a car that just *works* for a good amount of time, without costing a fortune in repairs. The good news? With a bit of care and attention, it's entirely possible to make your budget car last 2 years, or even longer, proving that cheap doesn't have to mean short-lived.\n\nHere at BuyAndScrap.com, we understand the value of making your money go further. So, let's dive into some practical, no-nonsense tips to help you get the most out of your affordable motor.\n\n## The Power of Regular Maintenance (Even if it’s DIY!)\n\nThis is hands-down the most crucial step if you want to know how to make your budget car last 2 years. Skipping maintenance to save a few quid now almost always costs you a lot more down the line.\n\n### Don't Skip Your MOT\n\nWhile the MOT is primarily a safety check, it’s also a good annual health check for your car. Any 'advisories' should be taken seriously. They're not just suggestions; they're warnings about potential issues that could become big problems.\n\n### Oil Changes are Non-Negotiable\n\nEngine oil is your car's lifeblood. It lubricates moving parts, reduces friction, and keeps the engine cool. Old, dirty oil can cause serious engine damage. Check your car's manual for the recommended interval, but generally, every 6,000-10,000 miles or once a year is a good shout. It's often an easy DIY job if you're feeling handy, saving you garage fees.\n\n### Check Your Fluids Regularly\n\nBeyond oil, your car relies on several other fluids: coolant, brake fluid, power steering fluid, and windscreen washer fluid. A quick check under the bonnet once a month can reveal low levels before they cause an issue. Topping these up is usually simple and cheap.\n\n### Tyres: The Only Bit Touching the Road\n\nProperly inflated tyres not only improve fuel economy but also reduce wear and tear on your suspension and brakes. Check your tyre pressure weekly and look for even wear. Rotate your tyres every 6 months or so to ensure they wear down evenly, extending their life.\n\n## Drive Smart, Not Hard\n\nYour driving style has a massive impact on your car's longevity, especially for an older or budget model.\n\n### Smooth Operator\n\nAvoid harsh acceleration and sudden braking. This puts less strain on your engine, transmission, brakes, and suspension. Anticipate traffic and give yourself plenty of time to slow down. Think of it as being gentle with your car; it'll thank you for it.\n\n### Mind Those Potholes!\n\nUK roads are notorious for potholes. Hitting them hard can damage tyres, wheels, suspension components, and even steering. Try to avoid them where safe to do so. If you can't, slow down as much as possible before impact.\n\n## Address Small Problems Early\n\nGot a strange noise? A dashboard warning light? Don't ignore it! That faint squeak could turn into a major repair if left unattended. Early diagnosis and repair of minor issues are key to making your budget car last 2 years without massive bills. A local, independent mechanic is often more affordable than main dealers for these kinds of fixes.\n\n## Keep it Clean and Protected\n\nBelieve it or not, a clean car lasts longer. Washing your car regularly, especially in winter, helps prevent rust, which can be a real killer for older vehicles. If you can, park under cover or use a car cover to protect it from harsh weather and UV rays.\n\n## How to Make Your Budget Car Last 2 Years: The Bottom Line\n\nGetting a couple of solid years out of a budget car isn't about luck; it's about proactive care and smart driving. Treat your car well, listen to its warning signs, and don't skimp on the basics. Following these tips will significantly increase your chances of keeping your reliable runner on the road and your wallet happier.\n\nWhen the time eventually comes to move on, whether it's for an upgrade or because the repairs outweigh the value, remember BuyAndScrap.com is here to help you get the best price for your old vehicle. But for now, get out there and enjoy those miles!\n\n[Browse Budget Cars](/cars)",
  "wordCount": 701,
  "cta": "Browse Budget Cars",
  "ctaLink": "/cars"
}