{
  "slug": "how-long-does-it-take-to-scrap-a-car",
  "title": "How Long Does It Take to Scrap a Car?",
  "metaDescription": "Wondering how long does it take to scrap a car in the UK? Get a quick answer and a breakdown of the entire process, from quote to collection, with BuyAndScrap.com.",
  "targetKeyword": "how long does it take to scrap a car",
  "intent": "informational",
  "pillar": "scrapping",
  "internalLinks": [
    "what-is-my-scrap-car-worth",
    "how-to-prepare-car-for-scrap"
  ],
  "content": "# How Long Does It Take to Scrap a Car?\n\nThinking about getting rid of that old banger and wondering **how long does it take to scrap a car**? Good news – the actual collection often takes just minutes! While there are a few steps involved from quote to collection, a smooth experience with a reputable service like BuyAndScrap.com means you can usually clear your driveway within a few days of making the decision.\n\nLet's break down the typical timeline.\n\n## The Quick Answer: How Long Does It *Really* Take to Scrap a Car?\n\nWhen people ask **how long does it take to scrap a car**, they often mean the moment the driver arrives until the car is gone. This part is genuinely fast – usually between 15 to 30 minutes! The overall journey, including getting a quote and scheduling, typically takes a few hours to a few days, depending on your availability.\n\n## Breaking Down the Scrap Car Timeline\n\nHere's a step-by-step look at the typical process:\n\n### Getting Your Instant Quote (Minutes)\n\nThe first step is getting a price. With BuyAndScrap.com, this is super quick. Just enter your car's registration and a few basic details online, and you'll receive an instant, no-obligation quote. No waiting around – just a clear price.\n\n### Accepting Your Offer & Arranging Collection (Hours to a Few Days)\n\nHappy with your quote? Great! Accept the offer and arrange a collection time that suits you. This can often be done the same day. We offer flexible collection slots across the UK, usually within 1-3 working days.\n\n### The Day of Collection (15-30 Minutes)\n\nThis is the big day! Our friendly collection agent will arrive at the agreed time. Here’s what usually happens:\n\n*   **Quick Check:** A brief visual check of the vehicle.\n*   **Paperwork:** Provide your ID and the V5C logbook (don't worry if it's misplaced, we can still collect).\n*   **Payment:** You’ll receive payment for your car.\n*   **Loading:** The car will be loaded onto the recovery vehicle.\n*   **Goodbye!** Your car is gone!\n\nThis interaction is designed to be quick and hassle-free, taking less than half an hour.\n\n### Post-Collection Paperwork (Minutes for You, Days for DVLA)\n\nEven after your car is gone, there's one crucial step: notifying the DVLA.\n\n*   **Certificate of Destruction (CoD):** If scrapped, the Authorised Treatment Facility (ATF) will issue a CoD as proof your car was correctly processed. You should receive this soon after collection.\n*   **Notifying DVLA:** You *must* inform the DVLA. Do this quickly online using your V5C reference number, or by post. Online notification is instant and recommended; DVLA updates records usually within a few working days.\n\n## What Can Delay the Scrap Process?\n\nWhile we aim for speed, a few things can slow it down:\n\n*   **Missing V5C Logbook:** Not a deal-breaker, but can add a small admin step.\n*   **Inaccessible Vehicle:** If your car is difficult to reach, it might take longer to load. Ensure clear access.\n*   **Incorrect Information:** Inaccurate car details can lead to delays.\n*   **Choosing the Wrong Buyer:** Not all scrap services are efficient. Choose a reputable company like BuyAndScrap.com for a smooth experience.\n\n## Top Tips for a Smooth Scrap Car Experience\n\nWant everything to run like clockwork?\n\n1.  **Have Your Documents Ready:** Your V5C logbook and ID are essential.\n2.  **Clear Access:** Park your car in an easily accessible spot for the collection vehicle.\n3.  **Remove Personal Belongings:** Double-check your glove box, boot, and under seats for any personal items you want to keep.\n4.  **Choose a Reputable Buyer:** BuyAndScrap.com works with Authorised Treatment Facilities (ATFs) for legal, environmentally friendly disposal, speedy collection, and fair prices. For more on getting the best value, check out [what-is-my-scrap-car-worth]. For preparing your car, see [how-to-prepare-car-for-scrap].\n\n## Ready to Scrap Your Car Quickly?\n\nSo, **how long does it take to scrap a car**? From getting your initial quote to saying farewell, the process can often be completed within a few days, with collection taking less than an hour. We make it straightforward and efficient.\n\nWhy not get an instant quote today and see how easy it is?\n\n[Sell Your Car](/sell)",
  "wordCount": 605,
  "cta": "Sell Your Car",
  "ctaLink": "/sell"
}